deployplex/__init__.py
deployplex/integrations/__init__.py
deployplex/integrations/fastapi.py
deployplex-0.0.10.dist-info/LICENSE
deployplex-0.0.10.dist-info/METADATA
deployplex-0.0.10.dist-info/WHEEL
deployplex-0.0.10.dist-info/RECORD
