Metadata-Version: 2.1
Name: deployplex
Version: 0.0.10
Summary: DeployPlex Python SDK
License: Apache-2.0
Author: Alvaro Molina
Author-email: am@deployplex.com
Requires-Python: >=3.11,<4.0
Classifier: License :: OSI Approved :: Apache Software License
Classifier: Programming Language :: Python :: 3
Classifier: Programming Language :: Python :: 3.11
Requires-Dist: fastapi (>=0.104.1,<0.105.0)
